vigorish/__init__.py
vigorish/app.py
vigorish/constants.py
vigorish/database.py
vigorish/enums.py
vigorish/types.py
vigorish/version.py
vigorish/cli/__init__.py
vigorish/cli/click_params.py
vigorish/cli/main_menu.py
vigorish/cli/menu.py
vigorish/cli/menu_item.py
vigorish/cli/vig.py
vigorish/cli/components/__init__.py
vigorish/cli/components/data_set_check.py
vigorish/cli/components/date_input.py
vigorish/cli/components/job_name_input.py
vigorish/cli/components/prompts.py
vigorish/cli/components/util.py
vigorish/cli/components/viewers/__init__.py
vigorish/cli/components/viewers/csv_viewer.py
vigorish/cli/components/viewers/dict_viewer.py
vigorish/cli/components/viewers/display_page.py
vigorish/cli/components/viewers/display_table.py
vigorish/cli/components/viewers/page_viewer.py
vigorish/cli/components/viewers/table_viewer.py
vigorish/cli/components/viewers/util.py
vigorish/cli/menu_items/__init__.py
vigorish/cli/menu_items/change_config_setting.py
vigorish/cli/menu_items/change_env_var_setting.py
vigorish/cli/menu_items/combine_data.py
vigorish/cli/menu_items/config_setting.py
vigorish/cli/menu_items/create_job.py
vigorish/cli/menu_items/exit_program.py
vigorish/cli/menu_items/investigate_data_failures.py
vigorish/cli/menu_items/investigate_invalid_pfx.py
vigorish/cli/menu_items/investigate_pitchfx_errors.py
vigorish/cli/menu_items/job_details.py
vigorish/cli/menu_items/return_to_parent.py
vigorish/cli/menu_items/setup_db.py
vigorish/cli/menu_items/status_report.py
vigorish/cli/menu_items/view_game_data.py
vigorish/cli/menu_items/admin_tasks/__init__.py
vigorish/cli/menu_items/admin_tasks/add_to_database.py
vigorish/cli/menu_items/admin_tasks/backup_database.py
vigorish/cli/menu_items/admin_tasks/calculate_avg_pitch_times.py
vigorish/cli/menu_items/admin_tasks/fix_orphaned_player_ids.py
vigorish/cli/menu_items/admin_tasks/import_scraped_data.py
vigorish/cli/menu_items/admin_tasks/npm_install_update.py
vigorish/cli/menu_items/admin_tasks/restore_database.py
vigorish-0.7.0.dist-info/LICENSE
vigorish-0.7.0.dist-info/METADATA
vigorish-0.7.0.dist-info/WHEEL
vigorish-0.7.0.dist-info/entry_points.txt
vigorish-0.7.0.dist-info/top_level.txt
vigorish-0.7.0.dist-info/RECORD
