Metadata-Version: 2.1
Name: vigorish
Version: 0.7.0
Summary: Hybrid Python/Node.js web scraper for Major League Baseball (MLB) data.
Home-page: https://github.com/a-luna/vigorish
Author: Aaron Luna
Author-email: contact@aaronluna.dev
Maintainer: Aaron Luna
Maintainer-email: contact@aaronluna.dev
License: MIT
Project-URL: Bug Tracker, https://github.com/a-luna/vigorish/issues
Project-URL: Source Code, https://github.com/a-luna/vigorish
Project-URL: Documentation, https://aaronluna.dev/projects/vigorish
Platform: UNKNOWN
Classifier: Development Status :: 4 - Beta
Classifier: Environment :: Console
Classifier: Intended Audience :: Developers
Classifier: License :: OSI Approved :: MIT License
Classifier: Natural Language :: English
Classifier: Operating System :: MacOS :: MacOS X
Classifier: Operating System :: POSIX :: Linux
Classifier: Operating System :: Unix
Classifier: Programming Language :: JavaScript
Classifier: Programming Language :: Python :: 3.8
Classifier: Programming Language :: Python :: 3.9
Classifier: Programming Language :: Python :: 3 :: Only
Requires-Python: >=3.6
License-File: LICENSE
Requires-Dist: aenum
Requires-Dist: boto3
Requires-Dist: bullet
Requires-Dist: click
Requires-Dist: dacite
Requires-Dist: dataclass-csv
Requires-Dist: enlighten
Requires-Dist: events
Requires-Dist: halo
Requires-Dist: lxml
Requires-Dist: naked
Requires-Dist: py-getch
Requires-Dist: pyfiglet
Requires-Dist: python-dateutil
Requires-Dist: python-dotenv
Requires-Dist: rapidfuzz
Requires-Dist: requests
Requires-Dist: scipy
Requires-Dist: sqlalchemy
Requires-Dist: sqlalchemy-utils
Requires-Dist: tabulate
Requires-Dist: tqdm
Requires-Dist: urllib3
Requires-Dist: w3lib
